Metadata-Version: 2.1
Name: algodocs
Version: 1.0
Summary: A python client for the AlgoDocs API
Home-page: https://github.com/algodocs/algodocs-python
Author: Ibrahim Nalbant
Author-email: support@algodocs.com
License: MIT
Keywords: AlgoDocs,API
Platform: UNKNOWN
License-File: LICENSE.txt
